c_krill/__init__.py
c_krill/core.py
c_krill/generate_json.py
c_krill/util.py
c_krill/krill.egg-info/PKG-INFO
c_krill/krill.egg-info/SOURCES.txt
c_krill/krill.egg-info/dependency_links.txt
c_krill/krill.egg-info/top_level.txt
c_krill/lib/lib.lib
c_krill/lib/liblogger.dll
c_krill/lib/liblogger.dll.obj
c_krill/lib/liblogger.dylib
c_krill/lib/liblogger.dylib.o
c_krill/lib/liblogger.pdb
c_krill/lib/liblogger.so
c_krill/lib/liblogger.so.o
c_krill/test/test_core.py
c_krill/test/test_generate_json.py
c_krill-0.0.11.dist-info/METADATA
c_krill-0.0.11.dist-info/WHEEL
c_krill-0.0.11.dist-info/licenses/LICENSE
c_krill-0.0.11.dist-info/RECORD
