Metadata-Version: 2.2
Name: c_krill
Version: 0.0.11
Summary: Python logging library that works with JSON
Author-email: ryotarofr <ryoryo.fr0608@gmail.com>
License: MIT License
License-File: LICENSE
Keywords: c_krill,log,logger,logging
Requires-Python: >=3.4
